basicsound/__init__.py
basicsound-0.0.1.dist-info/LICENSE.txt
basicsound-0.0.1.dist-info/METADATA
basicsound-0.0.1.dist-info/WHEEL
basicsound-0.0.1.dist-info/top_level.txt
basicsound-0.0.1.dist-info/RECORD
